tfdancing/__init__.py
tfdancing/__main__.py
tfdancing/cbb_brackets.py
tfdancing/wn_cbb_elo.py
tfdancing-0.1.3.dist-info/LICENSE
tfdancing-0.1.3.dist-info/METADATA
tfdancing-0.1.3.dist-info/WHEEL
tfdancing-0.1.3.dist-info/top_level.txt
tfdancing-0.1.3.dist-info/RECORD
