Metadata-Version: 2.1
Name: tfdancing
Version: 0.1.3
Summary: March Madness Bracket Pool Simulator
Author-email: Taylor Firman <tefirman@gmail.com>
Maintainer-email: Taylor Firman <tefirman@gmail.com>
License: MIT License
Project-URL: Homepage, https://taylorfirman.com
Project-URL: Repository, https://github.com/tefirman/dancing.git
Project-URL: Bug Tracker, https://github.com/tefirman/dancing/issues
Keywords: college basketball,warren nolan
Classifier: Programming Language :: Python :: 3
Classifier: License :: OSI Approved :: MIT License
Classifier: Operating System :: OS Independent
Requires-Python: >=3.8
License-File: LICENSE
Requires-Dist: numpy
Requires-Dist: pandas
Requires-Dist: beautifulsoup4
Requires-Dist: requests
Requires-Dist: lxml
